[
  {
    "Title": "Building a project that target .NET Framework 4.5 in Visual Studio 2022",
    "Url": "https://thomaslevesque.com/2021/11/12/building-a-project-that-target-net-45-in-visual-studio-2022/",
    "Timestamp": "2021-11-12T03:02:26",
    "Domain": "thomaslevesque.com",
    "Description": "I maintain a few libraries that still target .NET Framework 4.5 (among others). .NET 4.5 has long been out of support, but I try to keep supporting older frameworks in my libraries as long as it’s not a major inconvenience, because many people maintain old applications that can’t easily be updated to a newer framework.\nAnyway, until recently, supporting .NET 4.5 wasn’t much of a problem, but today I hit a snag… Before installing VS 2022 on my Surface Pro, I removed VS 2019 and old versions of ."
  },
  {
    "Title": "Setting up Serilog in .NET 6",
    "Url": "https://blog.datalust.co/using-serilog-in-net-6/",
    "Timestamp": "2021-11-12T02:02:17",
    "Domain": "blog.datalust.co",
    "Description": ".NET 6 is officially here! A lot has changed under the hood, and if you're kicking off a new project, a lot has changed on the surface, too. For starters, a minimal ASP.NET Core application created using dotnet new web: Doesn't have an explicit Program class, Startup class, or"
  }
]