[
  {
    "Title": "Home Assistant Config by Denys Dovhan - War Safety",
    "Url": "https://denysdovhan.com/home-assistant-config/config/war/",
    "Timestamp": "2024-05-26T12:01:03",
    "Domain": "denysdovhan.com",
    "Description": "🏡 My home automation setup built with Home Assistant"
  },
  {
    "Title": "Understanding and Utilizing Common Attributes in Classes in Microsoft .NET",
    "Url": "https://dotnettips.wordpress.com/2024/05/26/understanding-and-utilizing-common-attributes-in-classes-in-microsoft-net/",
    "Timestamp": "2024-05-26T09:00:59",
    "Domain": "dotnettips.wordpress.com",
    "Description": "Attributes for class members offer metadata and instructions for interaction with those members. This post highlights common member attributes like DebuggerDisplay, DefaultValue, DisallowNull, Edit…"
  }
]