[
  {
    "Title": "Mozilla launching \"Thundermail\" email service to take on Gmail, Microsoft 365",
    "Url": "https://www.techradar.com/pro/mozilla-launching-thundermail-email-service-to-take-on-gmail-microsoft-365",
    "Timestamp": "2025-04-03T04:02:10",
    "Domain": "www.techradar.com",
    "Description": "Thunderbird is getting a bunch of new features"
  },
  {
    "Title": "Interview with Vibe Coder in 2025",
    "Url": "https://youtube.com/watch?v=JeNS1ZNHQs8",
    "Timestamp": "2025-04-03T03:02:24",
    "Domain": "youtube.com",
    "Description": "Vibe Coding\n\nhttps://linkgraph.net/stack/vibecoder\n\nInterview with a Professional Vibe Coder with Kai Lentit  aired on © The Viboe Coder 2025.\n\nAI coding\nprompt engineering\nthree js\nwindsurf\nreplit\ncursor tricks\ncursor rules\nProgrammer humor\nVibe code Jam\nJavascript humor\nProgramming jokes\nProgramming memes\njs jokes\nState of AI coding 2025\nJunior Frontend Job Interview\n\n\n\n#vibecoding \n#jokes\n#programming"
  },
  {
    "Title": "hacker labs · pico.sh",
    "Url": "https://pico.sh/",
    "Timestamp": "2025-04-03T02:02:17",
    "Domain": "pico.sh",
    "Description": "Open source and managed web services leveraging SSH"
  },
  {
    "Title": "Decay Chain",
    "Url": "https://xkcd.com/3071/",
    "Timestamp": "2025-04-03T02:02:17",
    "Domain": "xkcd.com",
    "Description": ""
  }
]