[
  {
    "Title": "GraphQL: From Excitement to Deception",
    "Url": "https://betterprogramming.pub/graphql-from-excitement-to-deception-f81f7c95b7cf",
    "Timestamp": "2023-04-08T16:02:11",
    "Domain": "betterprogramming.pub",
    "Description": "Should you consider GraphQL?"
  },
  {
    "Title": "Paleontology Museum",
    "Url": "https://xkcd.com/2760/",
    "Timestamp": "2023-04-08T03:01:59",
    "Domain": "xkcd.com",
    "Description": ""
  },
  {
    "Title": "Edge AI Just Got Faster",
    "Url": "https://justine.lol/mmap/",
    "Timestamp": "2023-04-08T00:02:12",
    "Domain": "justine.lol",
    "Description": "Using mmap() to load LLaMA faster in parallel with less memory."
  }
]