[
  {
    "Title": "How to drive away your best engineers. | Hulacorn Blog",
    "Url": "https://blog.hulacorn.com/2021/09/08/how-to-drive-away-your-best-engineers/",
    "Timestamp": "2022-07-24T08:02:41",
    "Domain": "blog.hulacorn.com",
    "Description": "Tenures are at an all-time low in the software industry."
  },
  {
    "Title": "Thank-you GitHub!",
    "Url": "https://blog.taranissoftware.com/thank-you-github",
    "Timestamp": "2022-07-24T01:02:36",
    "Domain": "blog.taranissoftware.com",
    "Description": "Recently GitHub hosted Maintainer Month to support open source maintainers and distributed $500,000 to over 900 maintainers including me. Thank-you GitHub!"
  }
]