[
  {
    "Title": "Animation: The James Webb Space Telescope's Orbit",
    "Url": "https://www.youtube.com/watch?v=6cUe4oMk69E",
    "Timestamp": "2021-12-25T14:02:21",
    "Domain": "www.youtube.com",
    "Description": "James Webb Space Telescope orbit as seen from above the Sun's north pole and as seen from Earth's perspective.The James Webb Space Telescope will not be in o..."
  },
  {
    "Title": "As and Is Operators in C# - Code Maze",
    "Url": "https://code-maze.com/csharp-as-is-operators/",
    "Timestamp": "2021-12-25T09:02:14",
    "Domain": "code-maze.com",
    "Description": "In this article, we will learn about the type-testing as and is operators in C#, talk about each in detail and teach you when to use them."
  },
  {
    "Title": "Toyota 'Reviewing' Key Fob Remote Start Subscription Plan After Massive Blowback",
    "Url": "https://www.thedrive.com/news/43636/toyota-reviewing-key-fob-remote-start-subscription-plan-after-massive-blowback",
    "Timestamp": "2021-12-25T08:01:38",
    "Domain": "www.thedrive.com",
    "Description": "A spokesperson told The Drive that making the key fob remote start part of a subscription plan was an \"unintentional\" move."
  },
  {
    "Title": "REVEALED: The Legend of the 10MB Commodore D9090!",
    "Url": "https://www.youtube.com/watch?v=M8TGr3PJsok",
    "Timestamp": "2021-12-25T08:01:38",
    "Domain": "www.youtube.com",
    "Description": "Dave undertakes the Christmas challenge of finding, repairing, testing, and demoing a super-rare Commodore D9090!"
  },
  {
    "Title": "BGPStream Event #285778",
    "Url": "https://bgpstream.com/event/285778",
    "Timestamp": "2021-12-25T07:02:05",
    "Domain": "bgpstream.com",
    "Description": "Beginning at 2021-12-25 01:54:45, we detected a possible BGP hijack."
  },
  {
    "Title": "ADHD Accommodations Guide | ADHD At Work",
    "Url": "https://adhdatwork.add.org/adhd-accommodation-guide/",
    "Timestamp": "2021-12-25T06:01:50",
    "Domain": "adhdatwork.add.org",
    "Description": "Employer If you're an employer looking for ways to help your employee with ADHD perform better, you may want to visit the following pages: Providing Accommodations at Work Strengths-Based Approach to Managing ADHD @ Work Job Redesign for ADHD Below is a non-exhaustive list of accommodations many adults with ADHD have found helpful. It is […]"
  },
  {
    "Title": "Street Fighter II, Spin when you can't",
    "Url": "https://fabiensanglard.net/sf2_spin/index.html",
    "Timestamp": "2021-12-25T05:01:49",
    "Domain": "fabiensanglard.net",
    "Description": "Dec 24, 2021"
  },
  {
    "Title": "Street Fighter II, subtile accurate animation",
    "Url": "https://fabiensanglard.net/sf2_health_bar/index.html",
    "Timestamp": "2021-12-25T05:01:48",
    "Domain": "fabiensanglard.net",
    "Description": "Dec 25, 2021"
  },
  {
    "Title": "December 25th Launch",
    "Url": "https://xkcd.com/2559/",
    "Timestamp": "2021-12-25T05:01:48",
    "Domain": "xkcd.com",
    "Description": ""
  },
  {
    "Title": "BGPStream Event #285787",
    "Url": "https://bgpstream.com/event/285787",
    "Timestamp": "2021-12-25T04:02:20",
    "Domain": "bgpstream.com",
    "Description": "Beginning at 2021-12-25 01:54:45, we detected a possible BGP hijack."
  }
]