[
  {
    "Title": "Twitch Alerts - More Harm than Good?",
    "Url": "https://youtube.com/watch?v=RX6My6zmf0U",
    "Timestamp": "2023-05-31T00:02:02",
    "Domain": "youtube.com",
    "Description": "In May 2023, Twitch introduced a new native alert system for their video streaming platform.  New features means good things for creators, right?  Not always..."
  },
  {
    "Title": "Kilka milionów loginów i haseł z Polski wyciekło do sieci | Zaufana Trzecia Strona",
    "Url": "https://zaufanatrzeciastrona.pl/post/kilka-milionow-loginow-i-hasel-z-polski-wycieklo-do-sieci/",
    "Timestamp": "2023-05-31T00:02:01",
    "Domain": "zaufanatrzeciastrona.pl",
    "Description": ""
  }
]