[
  {
    "Title": "Part 1: How We Fell Out of Love with Next.js and Back in Love with Ruby on Rails & Inertia.js - Hardcover Blog",
    "Url": "https://hardcover.app/blog/part-1-how-we-fell-out-of-love-with-next-js-and-back-in-love-with-ruby-on-rails-inertia-js",
    "Timestamp": "2025-05-04T00:02:10",
    "Domain": "hardcover.app",
    "Description": "A look at how and why we migrated from Next.js to Ruby on Rails."
  },
  {
    "Title": "Best PDF Editor | Edit, Sign, Merge & Secure",
    "Url": "https://breezepdf.com/",
    "Timestamp": "2025-05-04T00:02:10",
    "Domain": "breezepdf.com",
    "Description": "Edit PDFs with ease—add text, images, signatures, merge files, create fillable forms, and password protect documents. Try our all-in-one PDF editor now!"
  }
]