[
  {
    "Title": "PeerTube v4, more power to help you present your videos",
    "Url": "https://framablog.org/2021/11/30/peertube-v4-more-power-to-help-you-present-your-videos/",
    "Timestamp": "2021-12-01T00:02:26",
    "Domain": "framablog.org",
    "Description": "Customization, content discovery, empowering through more control... Here is an overview of the new version of our software solution to create alternative platforms to YouTube and federate them together. « Frama is not just... » Each week of Fall 2021, we want to present you the diversity of what Framasoft does. As these actions are..."
  },
  {
    "Title": "DESQview/X : The forgotten mid-1990s OS from the future",
    "Url": "https://lunduke.substack.com/p/desqviewx-the-forgotten-mid-1990s",
    "Timestamp": "2021-12-01T00:02:22",
    "Domain": "lunduke.substack.com",
    "Description": "X11 client and server. DOS. Windows 3.1. All with preemptive multitasking."
  }
]