[
  {
    "Title": "rsync, article 3: How does rsync work?",
    "Url": "https://michael.stapelberg.ch/posts/2022-07-02-rsync-how-does-it-work/",
    "Timestamp": "2022-07-03T02:01:41",
    "Domain": "michael.stapelberg.ch",
    "Description": "This post is the third article in a series of blog posts about rsync, see the Series Overview.\nWith rsync up and running, it’s time to take a peek under the hood of rsync to better understand how it works."
  },
  {
    "Title": "Is Your Project Manager A Sith Lord? Three Ways To Find Out.",
    "Url": "https://sebastiancarlos.medium.com/is-your-project-manager-a-sith-lord-three-ways-to-find-out-822dbe5a1aa4",
    "Timestamp": "2022-07-03T01:01:30",
    "Domain": "sebastiancarlos.medium.com",
    "Description": "1. He deals in absolutes."
  }
]