[
  {
    "Title": "The Fall of Stack Overflow, Explained",
    "Url": "https://newsletter.devmoh.co/p/the-fall-of-stack-overflow-explained?r=1nwcx",
    "Timestamp": "2023-08-01T03:03:17",
    "Domain": "newsletter.devmoh.co",
    "Description": "Stack Overflow's decline is partly self-imposed, but also somewhat out if its control."
  },
  {
    "Title": "Bing Preview Release Notes: Dark Mode",
    "Url": "https://blogs.bing.com/search/july-2023/Bing-Preview-Release-Notes-Dark-Mode",
    "Timestamp": "2023-08-01T00:03:16",
    "Domain": "blogs.bing.com",
    "Description": "This week, browsing the web just got easier on your eyes and better for your laptop battery—we released dark mode for Bing Chat! This feature now works in both Bing Chat and Bing Chat Enterprise in your desktop browser, and it’s already available in the Bing mobile app. Dark mode also changes the appearance of the search page on Bing.com. \n"
  }
]