[
  {
    "Title": "VIBECHART.NET - The Art of Subjective Data Visualization",
    "Url": "https://www.vibechart.net/",
    "Timestamp": "2025-08-08T00:02:29",
    "Domain": "www.vibechart.net",
    "Description": "Vibecharting: To chart based on what you want to see instead of what is true, beautiful, or useful. The art of subjective data visualization."
  },
  {
    "Title": "Noteflakes - P2 - a Functional HTML Templating Engine for Ruby",
    "Url": "https://noteflakes.com/articles/2025-08-07-introducing-p2",
    "Timestamp": "2025-08-08T00:02:26",
    "Domain": "noteflakes.com",
    "Description": "I’ve just released P2, a new HTML\ntemplating engine for Ruby. P2 builds on the work I did in\nPapercraft, but takes things quite a bit\nfarther: templates are expressed as plain procs and are automatically compiled\nin order to make it fast. How fast?"
  }
]